cnapy/__init__.py
cnapy/__main__.py
cnapy/appdata.py
cnapy/application.py
cnapy/core.py
cnapy/core_gui.py
cnapy/flux_vector_container.py
cnapy/resources.py
cnapy/utils.py
cnapy/utils_for_cnapy_api.py
cnapy/data/blank.svg
cnapy/data/check.svg
cnapy/data/clear.svg
cnapy/data/cnapylogo.svg
cnapy/data/cnapylogo_no_text.svg
cnapy/data/cross.svg
cnapy/data/d-font.svg
cnapy/data/default-bg.svg
cnapy/data/default-color.svg
cnapy/data/escher.min.js
cnapy/data/escher_cnapy.html
cnapy/data/heat.svg
cnapy/data/onoff.svg
cnapy/data/qmark.svg
cnapy/data/redo.svg
cnapy/data/save.svg
cnapy/data/undo.svg
cnapy/data/zoom-in.svg
cnapy/data/zoom-out.svg
cnapy/gui_elements/__init__.py
cnapy/gui_elements/about_dialog.py
cnapy/gui_elements/annotation_widget.py
cnapy/gui_elements/box_position_dialog.py
cnapy/gui_elements/central_widget.py
cnapy/gui_elements/clipboard_calculator.py
cnapy/gui_elements/config_cobrapy_dialog.py
cnapy/gui_elements/config_dialog.py
cnapy/gui_elements/configuration_cplex.py
cnapy/gui_elements/configuration_gurobi.py
cnapy/gui_elements/download_dialog.py
cnapy/gui_elements/efm_dialog.py
cnapy/gui_elements/efmtool_dialog.py
cnapy/gui_elements/escher_map_view.py
cnapy/gui_elements/flux_feasibility_dialog.py
cnapy/gui_elements/flux_optimization_dialog.py
cnapy/gui_elements/gene_list.py
cnapy/gui_elements/in_out_flux_dialog.py
cnapy/gui_elements/main_window.py
cnapy/gui_elements/map_view.py
cnapy/gui_elements/mcs_dialog.py
cnapy/gui_elements/metabolite_list.py
cnapy/gui_elements/mode_navigator.py
cnapy/gui_elements/model_info.py
cnapy/gui_elements/plot_space_dialog.py
cnapy/gui_elements/reaction_table_widget.py
cnapy/gui_elements/reactions_list.py
cnapy/gui_elements/rename_map_dialog.py
cnapy/gui_elements/scenario_tab.py
cnapy/gui_elements/solver_buttons.py
cnapy/gui_elements/strain_design_dialog.py
cnapy/gui_elements/thermodynamics_dialog.py
cnapy/gui_elements/yield_optimization_dialog.py
cnapy/gui_elements/yield_space_dialog.py
cnapy-1.2.7.dist-info/licenses/LICENSE
cnapy-1.2.7.dist-info/METADATA
cnapy-1.2.7.dist-info/WHEEL
cnapy-1.2.7.dist-info/entry_points.txt
cnapy-1.2.7.dist-info/top_level.txt
cnapy-1.2.7.dist-info/RECORD
