Metadata-Version: 2.4
Name: cnapy
Version: 1.2.7
Summary: An integrated environment for metabolic network analysis.
Author: Sven Thiele, Axel von Kamp, Pavlos Stephanos Bekiaris, Philipp Schneider
Project-URL: Homepage, https://github.com/cnapy-org/CNApy
Project-URL: Issues, https://github.com/cnapy-org/CNApy/issues
Classifier: Programming Language :: Python :: 3
Classifier: License :: OSI Approved :: Apache Software License
Classifier: Operating System :: OS Independent
Requires-Python: ==3.10.*
License-File: LICENSE
Requires-Dist: appdirs>=1.4
Requires-Dist: matplotlib>=3.6
Requires-Dist: requests>=2.28
Requires-Dist: cobra>=0.30
Requires-Dist: efmtool_link>=0.0.8
Requires-Dist: optlang_enumerator>=0.0.12
Requires-Dist: straindesign>=1.12
Requires-Dist: qtpy>=2.3
Requires-Dist: pyqtwebengine>=5.15
Requires-Dist: qtconsole==5.4
Requires-Dist: gurobipy>=12.0
Requires-Dist: cplex==22.1.2.0
Requires-Dist: numpy==1.23
Requires-Dist: scipy==1.12
Requires-Dist: openpyxl
Requires-Dist: jpype1==1.5.0
Requires-Dist: setuptools
Requires-Dist: cobrak==0.0.2
Dynamic: license-file
